dtcm.py
dtcm-0.2.20.dist-info/LICENSE
dtcm-0.2.20.dist-info/METADATA
dtcm-0.2.20.dist-info/WHEEL
dtcm-0.2.20.dist-info/top_level.txt
dtcm-0.2.20.dist-info/RECORD
